securehst_webhook_notifier/__init__.py
securehst_webhook_notifier/main.py
securehst_webhook_notifier/py.typed
securehst_webhook_notifier-1.1.3.dist-info/licenses/LICENSE
securehst_webhook_notifier-1.1.3.dist-info/METADATA
securehst_webhook_notifier-1.1.3.dist-info/WHEEL
securehst_webhook_notifier-1.1.3.dist-info/top_level.txt
securehst_webhook_notifier-1.1.3.dist-info/RECORD
