Metadata-Version: 2.4
Name: securehst-webhook-notifier
Version: 1.1.3
Summary: This package helps monitor automation processes with real-time updates directly in various platforms.
Author-email: Mark Moreno <mark@securehst.com>
License: MIT
Project-URL: Bug Tracker, https://github.com/securehst/securehst-webhook-notifier/issues
Project-URL: Changelog, https://github.com/securehst/securehst-webhook-notifier/blob/main/CHANGELOG.md
Project-URL: documentation, https://securehst-webhook-notifier.readthedocs.io
Project-URL: repository, https://github.com/securehst/securehst-webhook-notifier
Classifier: Development Status :: 2 - Pre-Alpha
Classifier: Intended Audience :: Developers
Classifier: Natural Language :: English
Classifier: Operating System :: OS Independent
Classifier: Programming Language :: Python :: 3.10
Classifier: Programming Language :: Python :: 3.11
Classifier: Programming Language :: Python :: 3.12
Classifier: Programming Language :: Python :: 3.13
Classifier: Topic :: Software Development :: Libraries
Requires-Python: >=3.10
License-File: LICENSE
Requires-Dist: requests>=2.32.3
Requires-Dist: prefect>=2.0.0
Dynamic: license-file
